soniox/__init__.py
soniox/capture_device.py
soniox/conversion.py
soniox/manage_speakers.py
soniox/manage_speech_contexts.py
soniox/multi_channel_utils.py
soniox/speech_service.py
soniox/speech_service_pb2.py
soniox/speech_service_pb2.pyi
soniox/speech_service_pb2_grpc.py
soniox/storage.py
soniox/transcribe_file.py
soniox/transcribe_live.py
soniox/utils.py
soniox-1.10.1.dist-info/LICENSE
soniox-1.10.1.dist-info/METADATA
soniox-1.10.1.dist-info/WHEEL
soniox-1.10.1.dist-info/top_level.txt
soniox-1.10.1.dist-info/RECORD
