Metadata-Version: 2.1
Name: soniox
Version: 1.10.1
Summary: Soniox speech recognition service client library
Home-page: https://soniox.com/
Author: Soniox Inc
Author-email: support@soniox.com
Classifier: Programming Language :: Python :: 3
Classifier: License :: OSI Approved :: MIT License
Classifier: Operating System :: OS Independent
Requires-Python: >=3.7
License-File: LICENSE
Requires-Dist: protobuf>=3.20.0
Requires-Dist: grpcio>=1.46.0
Requires-Dist: numpy
Requires-Dist: SoundCard
